textlinebreaker/__init__.py
textlinebreaker/textlinebreaker.py
textlinebreaker-1.0.0.post6.dist-info/licenses/LICENSE.md
textlinebreaker-1.0.0.post6.dist-info/METADATA
textlinebreaker-1.0.0.post6.dist-info/WHEEL
textlinebreaker-1.0.0.post6.dist-info/top_level.txt
textlinebreaker-1.0.0.post6.dist-info/RECORD
