Metadata-Version: 2.4
Name: textlinebreaker
Version: 1.0.0.post6
Summary: A module to format strings with customizable line length and alignment. Fixes splitting issue (characters vs words) and adds input type detection (list or string).
Author-email: scalvaruso <calvaruso.simone@gmail.com>
License: MIT License
Project-URL: Homepage, https://pypi.org/project/textlinebreaker
Project-URL: Repository, https://github.com/scalvaruso/textlinebreaker
Project-URL: Issues, https://github.com/scalvaruso/textlinebreaker/issues
Keywords: alignment,break,center,centre,format,left,line,right,split,string,text,words
Classifier: Programming Language :: Python :: 3
Classifier: Programming Language :: Python :: 3.9
Classifier: Programming Language :: Python :: 3.10
Classifier: Programming Language :: Python :: 3.11
Classifier: License :: OSI Approved :: MIT License
Classifier: Operating System :: OS Independent
Requires-Python: >=3.9
License-File: LICENSE.md
Dynamic: license-file
